bearsql/__init__.py
bearsql/bearsql.py
bearsql/cli.py
bearsql/log_source.py
bearsql-0.1.0.dist-info/AUTHORS.rst
bearsql-0.1.0.dist-info/LICENSE
bearsql-0.1.0.dist-info/METADATA
bearsql-0.1.0.dist-info/WHEEL
bearsql-0.1.0.dist-info/entry_points.txt
bearsql-0.1.0.dist-info/top_level.txt
bearsql-0.1.0.dist-info/RECORD
