Metadata-Version: 2.1
Name: bearsql
Version: 0.1.0
Summary: Bearsql aadds sql syntax on pandas dataframe. It uses duckdb to speedup the pandas processing and as the sql engine
Home-page: https://github.com/shrinivdeshmukh/bearsql
Author: Shrinivas Vijay Deshmukh
Author-email: shrinivas.deshmukh11@gmail.com
License: MIT license
Keywords: bearsql
Platform: UNKNOWN
Classifier: Development Status :: 2 - Pre-Alpha
Classifier: Intended Audience :: Developers
Classifier: License :: OSI Approved :: MIT License
Classifier: Natural Language :: English
Classifier: Programming Language :: Python :: 3
Classifier: Programming Language :: Python :: 3.6
Classifier: Programming Language :: Python :: 3.7
Classifier: Programming Language :: Python :: 3.8
Requires-Python: >=3.6
Requires-Dist: coverage (==5.5)
Requires-Dist: duckdb (==0.2.7)
Requires-Dist: numpy (==1.21.0)
Requires-Dist: pandas (==1.2.5)
Requires-Dist: pyarrow (==4.0.1)
Requires-Dist: python-dateutil (==2.8.1)
Requires-Dist: pytz (==2021.1)
Requires-Dist: six (==1.16.0)
